deepke/__init__.py
deepke/transform_data.py
deepke/attribution_extraction/__init__.py
deepke/attribution_extraction/standard/__init__.py
deepke/attribution_extraction/standard/models/BasicModule.py
deepke/attribution_extraction/standard/models/BiLSTM.py
deepke/attribution_extraction/standard/models/Capsule.py
deepke/attribution_extraction/standard/models/GCN.py
deepke/attribution_extraction/standard/models/LM.py
deepke/attribution_extraction/standard/models/PCNN.py
deepke/attribution_extraction/standard/models/Transformer.py
deepke/attribution_extraction/standard/models/__init__.py
deepke/attribution_extraction/standard/module/Attention.py
deepke/attribution_extraction/standard/module/CNN.py
deepke/attribution_extraction/standard/module/Capsule.py
deepke/attribution_extraction/standard/module/Embedding.py
deepke/attribution_extraction/standard/module/GCN.py
deepke/attribution_extraction/standard/module/RNN.py
deepke/attribution_extraction/standard/module/Transformer.py
deepke/attribution_extraction/standard/module/__init__.py
deepke/attribution_extraction/standard/tools/__init__.py
deepke/attribution_extraction/standard/tools/dataset.py
deepke/attribution_extraction/standard/tools/metrics.py
deepke/attribution_extraction/standard/tools/preprocess.py
deepke/attribution_extraction/standard/tools/serializer.py
deepke/attribution_extraction/standard/tools/trainer.py
deepke/attribution_extraction/standard/tools/vocab.py
deepke/attribution_extraction/standard/utils/__init__.py
deepke/attribution_extraction/standard/utils/ioUtils.py
deepke/attribution_extraction/standard/utils/nnUtils.py
deepke/event_extraction/__init__.py
deepke/event_extraction/standard/__init__.py
deepke/event_extraction/standard/bertcrf/__init__.py
deepke/event_extraction/standard/bertcrf/bert_crf.py
deepke/event_extraction/standard/bertcrf/crf.py
deepke/event_extraction/standard/bertcrf/processor_ee.py
deepke/event_extraction/standard/bertcrf/utils_ee.py
mseep_deepke-2.2.7.dist-info/licenses/LICENSE
mseep_deepke-2.2.7.dist-info/METADATA
mseep_deepke-2.2.7.dist-info/WHEEL
mseep_deepke-2.2.7.dist-info/top_level.txt
mseep_deepke-2.2.7.dist-info/RECORD
