Metadata-Version: 2.4
Name: mseep-deepke
Version: 2.2.7
Summary: DeepKE is a knowledge extraction toolkit for knowledge graph construction supporting low-resource, document-level and multimodal scenarios for entity, relation and attribute extraction.
Home-page: https://github.com/zjunlp/deepke
Author: mseep
Author-email: zhangningyu@zju.edu.cn
Maintainer: mseep
Maintainer-email: support@skydeck.ai
License: MIT
Keywords: pip,RE,NER,AE
Platform: any
Classifier: Programming Language :: Python :: 3
Classifier: Operating System :: OS Independent
License-File: LICENSE
Dynamic: author
Dynamic: author-email
Dynamic: classifier
Dynamic: description
Dynamic: description-content-type
Dynamic: home-page
Dynamic: keywords
Dynamic: license
Dynamic: license-file
Dynamic: maintainer
Dynamic: maintainer-email
Dynamic: platform
Dynamic: summary
